maven_decoder_mcp/__init__.py
maven_decoder_mcp/config.py
maven_decoder_mcp/decompiler.py
maven_decoder_mcp/decompiler_paths.py
maven_decoder_mcp/maven_analyzer.py
maven_decoder_mcp/maven_decoder_server.py
maven_decoder_mcp-1.0.23.dist-info/licenses/LICENSE
scripts/release.py
tests/conftest.py
tests/test_pagination.py
maven_decoder_mcp-1.0.23.dist-info/METADATA
maven_decoder_mcp-1.0.23.dist-info/WHEEL
maven_decoder_mcp-1.0.23.dist-info/entry_points.txt
maven_decoder_mcp-1.0.23.dist-info/top_level.txt
maven_decoder_mcp-1.0.23.dist-info/RECORD
