Metadata-Version: 2.4
Name: maven-decoder-mcp
Version: 1.0.23
Summary: MCP server for reading and decompiling Maven .m2 jar files with comprehensive Java project analysis
Author-email: Ali Tabatabaei <ali79taba@gmail.com>
Maintainer-email: Ali Tabatabaei <ali79taba@gmail.com>
License: MIT
Project-URL: Homepage, https://github.com/salitaba/maven-decoder-mcp
Project-URL: Documentation, https://github.com/salitaba/maven-decoder-mcp#readme
Project-URL: Repository, https://github.com/salitaba/maven-decoder-mcp.git
Project-URL: Bug Tracker, https://github.com/salitaba/maven-decoder-mcp/issues
Keywords: mcp,maven,java,decompiler,jar,analysis,cursor,ide
Classifier: Development Status :: 4 - Beta
Classifier: Intended Audience :: Developers
Classifier: License :: OSI Approved :: MIT License
Classifier: Operating System :: OS Independent
Classifier: Programming Language :: Python :: 3
Classifier: Programming Language :: Python :: 3.8
Classifier: Programming Language :: Python :: 3.9
Classifier: Programming Language :: Python :: 3.10
Classifier: Programming Language :: Python :: 3.11
Classifier: Programming Language :: Python :: 3.12
Classifier: Topic :: Software Development :: Libraries :: Python Modules
Classifier: Topic :: Software Development :: Build Tools
Classifier: Topic :: Software Development :: Debuggers
Classifier: Topic :: Software Development :: Disassemblers
Requires-Python: >=3.10
License-File: LICENSE
Requires-Dist: mcp>=1.0.0
Requires-Dist: pydantic>=2.0.0
Requires-Dist: xmltodict>=0.13.0
Requires-Dist: javatools>=1.4.0
Requires-Dist: py4j>=0.10.9
Requires-Dist: aiofiles>=23.0.0
Requires-Dist: pathspec>=0.11.0
Requires-Dist: requests>=2.25.0
Provides-Extra: dev
Requires-Dist: pytest>=7.0.0; extra == "dev"
Requires-Dist: pytest-asyncio>=0.21.0; extra == "dev"
Requires-Dist: black>=23.0.0; extra == "dev"
Requires-Dist: isort>=5.12.0; extra == "dev"
Requires-Dist: mypy>=1.0.0; extra == "dev"
Requires-Dist: flake8>=6.0.0; extra == "dev"
Dynamic: license-file
